icon_font_to_png/__init__.py
icon_font_to_png/command_line.py
icon_font_to_png/icon_font.py
icon_font_to_png/icon_font_downloader.py
icon_font_to_png/test/test_command_line.py
icon_font_to_png/test/test_font_awesome.py
icon_font_to_png/test/test_icon_font.py
icon_font_to_png/test/test_icon_font_downloader.py
icon_font_to_png/test/test_octicons.py
icon_font_to_png/test/files/font-awesome.css
icon_font_to_png/test/files/fontawesome-webfont.ttf
icon_font_to_png/test/files/octicons.css
icon_font_to_png/test/files/octicons.ttf
icon_font_to_png/test/files/rocket_100.png
icon_font_to_png/test/files/rocket_123123.png
icon_font_to_png/test/files/rocket_16.png
icon_font_to_png/test/files/rocket_256.png
icon_font_to_png/test/files/rocket_auto.png
icon_font_to_png/test/files/rocket_blue.png
icon_font_to_png/test/files/rocket_cyan.png
icon_font_to_png/test/files/rocket_x05.png
icon_font_to_png/test/files/rocket_x1.png
icon_font_to_png/test/files/test-foo.css
icon_font_to_png/test/files/test.css
icon_font_to_png/test/files/test.ttf
icon_font_to_png-0.4.1.data/scripts/font-awesome-to-png
icon_font_to_png-0.4.1.data/scripts/icon-font-to-png
icon_font_to_png-0.4.1.dist-info/DESCRIPTION.rst
icon_font_to_png-0.4.1.dist-info/METADATA
icon_font_to_png-0.4.1.dist-info/RECORD
icon_font_to_png-0.4.1.dist-info/WHEEL
icon_font_to_png-0.4.1.dist-info/metadata.json
icon_font_to_png-0.4.1.dist-info/top_level.txt
