Metadata-Version: 1.1
Name: icon-font-to-png
Version: 0.4.1
Summary: Python script (and library) for exporting icons from icon fonts (e.g. Font Awesome, Octicons) as PNG images.
Home-page: https://github.com/Pythonity/icon-font-to-png
Author: Paweł Adamczak
Author-email: pawel.adamczak@sidnet.info
License: MIT License
Download-URL: https://github.com/Pythonity/icon-font-to-png/releases/latest
Keywords: icon font export font awesome octicons
Platform: UNKNOWN
Classifier: Development Status :: 4 - Beta
Classifier: Environment :: Console
Classifier: Intended Audience :: End Users/Desktop
Classifier: License :: OSI Approved :: MIT License
Classifier: Operating System :: OS Independent
Classifier: Programming Language :: Python
Classifier: Programming Language :: Python :: 2
Classifier: Programming Language :: Python :: 2.7
Classifier: Programming Language :: Python :: 3
Classifier: Programming Language :: Python :: 3.4
Classifier: Programming Language :: Python :: 3.5
Classifier: Programming Language :: Python :: 3.6
Classifier: Topic :: Utilities
